README.rst
setup.py
pgpubsub/__init__.py
pgpubsub/triggers.py
pgpubsub.egg-info/PKG-INFO
pgpubsub.egg-info/SOURCES.txt
pgpubsub.egg-info/dependency_links.txt
pgpubsub.egg-info/requires.txt
pgpubsub.egg-info/top_level.txt