Metadata-Version: 1.0
Name: pgpubsub
Version: 0.0.5
Summary: A convenient Python interface to Postgres's LISTEN and NOTIFY features.
Home-page: https://bitbucket.org/btubbs/pgpubsub
Author: Brent Tubbs
Author-email: brent.tubbs@gmail.com
License: UNKNOWN
Platform: UNKNOWN
